{"trial_id": "0005", "hyperparameters": {"space": [{"class_name": "Int", "config": {"name": "units", "default": null, "conditions": [], "min_value": 32, "max_value": 512, "step": 32, "sampling": "linear"}}, {"class_name": "Fixed", "config": {"name": "activation", "conditions": [], "value": "relu"}}], "values": {"units": 192, "activation": "relu", "tuner/epochs": 2, "tuner/initial_epoch": 0, "tuner/bracket": 2, "tuner/round": 0}}, "metrics": {"metrics": {"loss": {"direction": "min", "observations": [{"value": [0.6687371134757996], "step": 1}]}, "accuracy": {"direction": "max", "observations": [{"value": [0.5740165114402771], "step": 1}]}, "val_loss": {"direction": "min", "observations": [{"value": [0.6754840016365051], "step": 1}]}, "val_accuracy": {"direction": "max", "observations": [{"value": [0.5812245011329651], "step": 1}]}}}, "score": 0.5812245011329651, "best_step": 1, "status": "COMPLETED", "message": null}